quyuan/__init__.py
quyuan/_version.py
quyuan/base.svg.p
quyuan/chrom_sizes.json
quyuan/main.py
quyuan/scripts/LICENSE
quyuan/scripts/rfmix2tagore.py
quyuan-1.1.3.dist-info/LICENSE
quyuan-1.1.3.dist-info/METADATA
quyuan-1.1.3.dist-info/WHEEL
quyuan-1.1.3.dist-info/entry_points.txt
quyuan-1.1.3.dist-info/top_level.txt
quyuan-1.1.3.dist-info/RECORD
