Metadata-Version: 2.1
Name: quyuan
Version: 1.1.3
Summary: A simple way to visualize features on human and other species chromosome ideograms, folk of jordanlab/tagore
Author-email: Tang Ziya <tang@stu.njau.edu.cn>, Applied Bioinformatics Laboratory <abil@ihrc.com>
Project-URL: homepage, https://github.com/tcztzy/quyuan
Keywords: Human,chromosome,ideogram,visualization
Classifier: Programming Language :: Python :: 3
Classifier: License :: OSI Approved :: GNU General Public License v3 (GPLv3)
Classifier: Environment :: Console
Classifier: Development Status :: 5 - Production/Stable
Classifier: Topic :: Scientific/Engineering :: Visualization
Requires-Python: >=3.6
License-File: LICENSE
Requires-Dist: cairosvg
Requires-Dist: click
Requires-Dist: colorama
Requires-Dist: importlib-metadata ; python_version < "3.8"
Provides-Extra: test
Requires-Dist: pytest ; extra == 'test'
